fabtools/__init__.py
fabtools/apache.py
fabtools/arch.py
fabtools/cron.py
fabtools/deb.py
fabtools/disk.py
fabtools/files.py
fabtools/git.py
fabtools/group.py
fabtools/gvm.py
fabtools/mercurial.py
fabtools/mysql.py
fabtools/network.py
fabtools/nginx.py
fabtools/nodejs.py
fabtools/opkg.py
fabtools/oracle_jdk.py
fabtools/pkg.py
fabtools/portage.py
fabtools/postgres.py
fabtools/python.py
fabtools/python_setuptools.py
fabtools/rpm.py
fabtools/service.py
fabtools/shorewall.py
fabtools/ssh.py
fabtools/supervisor.py
fabtools/system.py
fabtools/systemd.py
fabtools/tomcat.py
fabtools/user.py
fabtools/utils.py
fabtools/vagrant.py
fabtools/openvz/__init__.py
fabtools/openvz/container.py
fabtools/openvz/contextmanager.py
fabtools/openvz/operations.py
fabtools/require/__init__.py
fabtools/require/apache.py
fabtools/require/arch.py
fabtools/require/curl.py
fabtools/require/deb.py
fabtools/require/files.py
fabtools/require/git.py
fabtools/require/groups.py
fabtools/require/mercurial.py
fabtools/require/mysql.py
fabtools/require/nginx.py
fabtools/require/nodejs.py
fabtools/require/openvz.py
fabtools/require/opkg.py
fabtools/require/oracle_jdk.py
fabtools/require/pkg.py
fabtools/require/portage.py
fabtools/require/postfix.py
fabtools/require/postgres.py
fabtools/require/python.py
fabtools/require/redis.py
fabtools/require/rpm.py
fabtools/require/service.py
fabtools/require/shorewall.py
fabtools/require/supervisor.py
fabtools/require/system.py
fabtools/require/tomcat.py
fabtools/require/users.py
fabtools/tests/__init__.py
fabtools/tests/test_apache.py
fabtools/tests/test_files.py
fabtools/tests/test_group.py
fabtools/tests/test_oracle_jdk.py
fabtools/tests/test_postgres.py
fabtools/tests/test_python.py
fabtools/tests/test_redis.py
fabtools/tests/test_shorewall.py
fabtools/tests/test_system.py
fabtools/tests/test_user.py
fabtools/tests/test_vagrant_base_boxes.py
fabtools/tests/test_vagrant_machines.py
fabtools3-0.19.0.dist-info/DESCRIPTION.rst
fabtools3-0.19.0.dist-info/METADATA
fabtools3-0.19.0.dist-info/RECORD
fabtools3-0.19.0.dist-info/WHEEL
fabtools3-0.19.0.dist-info/metadata.json
fabtools3-0.19.0.dist-info/top_level.txt
